ky/__init__.py
ky-0.0.5.dist-info/licenses/LICENSE
ky-0.0.5.dist-info/METADATA
ky-0.0.5.dist-info/WHEEL
ky-0.0.5.dist-info/top_level.txt
ky-0.0.5.dist-info/RECORD
