Metadata-Version: 2.4
Name: ky
Version: 0.0.5
Summary: Utils to work with dates
Home-page: https://github.com/t-c-w/ky
Author: Thor Whalen
License: apache-2.0
Platform: any
License-File: LICENSE
Dynamic: license-file
